dlog/__init__.py
dlog/source/__init__.py
dlog/source/logger.py
dlog/source/record.py
dlog/source/styles.py
dlog/source/utils.py
dlog/source/values.py
dLogpy-0.0.5.dist-info/LICENSE
dLogpy-0.0.5.dist-info/METADATA
dLogpy-0.0.5.dist-info/WHEEL
dLogpy-0.0.5.dist-info/top_level.txt
dLogpy-0.0.5.dist-info/RECORD
