Metadata-Version: 2.1
Name: dLogpy
Version: 0.0.5
Summary: Compact logger for Python 3.10+
Home-page: https://github.com/dim-4/dLog
Author: Vos
Author-email: your.email@example.com
Classifier: Development Status :: 3 - Alpha
Classifier: Intended Audience :: Developers
Classifier: License :: OSI Approved :: MIT License
Classifier: Programming Language :: Python :: 3.10
Classifier: Programming Language :: Python :: 3.11
License-File: LICENSE
